{
    "progettoId": 2854,
    "batteryType": "18650",
    "totalVoltage": 12.0,
    "totalBatteryCurrent": 20000.0,
    "ratedCapacity": 2000.0,
    "maxDischarge": 10.0,
    "nominalVoltage": 3.7,
    "maxChargeVoltage": 4.2,
    "chargingCurrent": 1.5,
    "disegnoJson": "{\"disegno\":{\"lines\":[{\"x1\":247,\"y1\":342,\"x2\":498,\"y2\":340},{\"x1\":498,\"y1\":340,\"x2\":497,\"y2\":201},{\"x1\":497,\"y1\":201,\"x2\":247,\"y2\":203},{\"x1\":247,\"y1\":203,\"x2\":247,\"y2\":342}],\"misure\":[\"251.01\",\"139.00\",\"250.01\",\"139.00\"],\"angoli\":[90,89.5,90,90.5],\"vertici\":[{\"x\":247,\"y\":178},{\"x\":498,\"y\":180},{\"x\":497,\"y\":319},{\"x\":247,\"y\":317}]}}"
}